setup.cfg
setup.py
simple_irc.py
simple_irc.egg-info/PKG-INFO
simple_irc.egg-info/SOURCES.txt
simple_irc.egg-info/dependency_links.txt
simple_irc.egg-info/top_level.txt