Metadata-Version: 1.0
Name: simple-irc
Version: 1.0
Summary: A simple, Pythonic IRC interface
Home-page: https://github.com/maxrothman/simple_irc
Author: Max Rothman
Author-email: max.r.rothman@gmail.com
License: UNKNOWN
Download-URL: https://github.com/maxrothman/simple_irc/tarball/1.0
Keywords: simple IRC
Platform: UNKNOWN
Classifier: Development Status :: 4 - Beta
Classifier: Intended Audience :: Developers
Classifier: License :: OSI Approved :: MIT License
Classifier: Topic :: Internet
Classifier: Topic :: Software Development :: Libraries
Classifier: Programming Language :: Python :: 2
Classifier: Programming Language :: Python :: 3
